<Properties StartupConfiguration="{67B5D7E2-6FAA-4409-9FB1-EC79E730E523}|Default">
  <MonoDevelop.Ide.Workbench ActiveDocument="AndroidRecorder/RecordingManager.cs">
    <Files>
      <File FileName="AndroidRecorder/DataManager.cs" Line="13" Column="50" />
      <File FileName="AndroidRecorder/ADBCommand.cs" Line="45" Column="59" />
      <File FileName="../../../../Library/Frameworks/Xamarin.Mac.framework/Versions/5.2.1.15/src/Xamarin.Mac/mcs/class/referencesource/mscorlib/system/runtime/exceptionservices/exceptionservicescommon.cs" Line="155" Column="1" />
      <File FileName="AndroidRecorder/ViewController.cs" Line="39" Column="1" />
      <File FileName="AndroidRecorder/SequenceManager.cs" Line="95" Column="40" />
      <File FileName="AndroidRecorder/ApplicationConfig.cs" Line="25" Column="1" NotebookId="1" />
      <File FileName="AndroidRecorder/DoBashCommand.cs" Line="27" Column="10" NotebookId="1" />
      <File FileName="AndroidRecorder/RecordingManager.cs" Line="71" Column="27" NotebookId="1" />
    </Files>
    <Pads>
      <Pad Id="ProjectPad">
        <State name="__root__">
          <Node name="AndroidRecorder" expanded="True">
            <Node name="AndroidRecorder" expanded="True">
              <Node name="RecordingManager.cs" selected="True" />
            </Node>
          </Node>
        </State>
      </Pad>
    </Pads>
  </MonoDevelop.Ide.Workbench>
  <MonoDevelop.Ide.DebuggingService.PinnedWatches />
  <MonoDevelop.Ide.Workspace ActiveConfiguration="Debug|x86" />
  <MonoDevelop.Ide.DebuggingService.Breakpoints>
    <BreakpointStore />
  </MonoDevelop.Ide.DebuggingService.Breakpoints>
  <MultiItemStartupConfigurations />
  <MonoDevelop.Ide.ItemProperties.AndroidRecorder PreferredExecutionTarget="Test1" />
</Properties>